LICENSE
MANIFEST.in
README
setup.cfg
setup.py
pysyslogclient/__init__.py
pysyslogclient/cli.py
pysyslogclient.egg-info/PKG-INFO
pysyslogclient.egg-info/SOURCES.txt
pysyslogclient.egg-info/dependency_links.txt
pysyslogclient.egg-info/top_level.txt