Metadata-Version: 1.1
Name: pysyslogclient
Version: 0.1.1
Summary: Syslog client implementation (RFC 3164/RFC 5424)
Home-page: https://github.com/aboehm/pysyslogclient
Author: Alexander Böhm
Author-email: alxndr.boehm@gmail.com
License: BSD-2-Clause
Keywords: syslog logging monitoring
Platform: UNKNOWN
Classifier: Development Status :: 5 - Production/Stable
Classifier: License :: OSI Approved :: BSD License
Classifier: Programming Language :: Python :: 3 :: Only
Classifier: Programming Language :: Python :: 3.5
Classifier: Programming Language :: Python :: 3.6
Classifier: Operating System :: Unix
Classifier: Operating System :: POSIX :: Linux
Classifier: Operating System :: Microsoft
Classifier: Topic :: System :: Logging
Classifier: Topic :: System :: Monitoring
